CHANGELOG.md
CONTRIBUTING.md
LICENSE
MANIFEST.in
Makefile
README.md
VERSION
setup.cfg
setup.py
docker/Dockerfile
docker/entrypoint-headless.sh
docker/entrypoint-runtime.sh
docker/hooks/build
docs/Makefile
docs/bibtex.json
docs/conf.py
docs/index.md
docs/requirements.txt
docs/_static/resl_logo.png
docs/_static/theme_overrides.css
docs/_static/viterbi_logo.png
docs/_templates/footer.html
docs/autoapi_templates/python/module.rst
docs/user/algo_bc.md
docs/user/algo_cem.md
docs/user/algo_ddpg.md
docs/user/algo_dqn.md
docs/user/algo_erwr.md
docs/user/algo_maml.md
docs/user/algo_mtppo.md
docs/user/algo_mtsac.md
docs/user/algo_mttrpo.md
docs/user/algo_pearl.md
docs/user/algo_ppo.md
docs/user/algo_rl2.md
docs/user/algo_sac.md
docs/user/algo_td3.md
docs/user/algo_trpo.md
docs/user/algo_vpg.md
docs/user/benchmarking.md
docs/user/cluster_setup.md
docs/user/concept_experiment.md
docs/user/custom_worker.md
docs/user/docker.md
docs/user/docker_dev.md
docs/user/ensure_your_experiments_are_reproducible.md
docs/user/environment.md
docs/user/environment_libraries.md
docs/user/experiments.rst
docs/user/get_started.md
docs/user/git_workflow.md
docs/user/implement_algo.md
docs/user/implement_env.md
docs/user/implement_env.rst
docs/user/implement_worker.md
docs/user/installation.rst
docs/user/logging_plotting.md
docs/user/matplotlib_example.png
docs/user/max_resource_usage.md
docs/user/meta_multi_task_rl_exp.md
docs/user/monitor_experiments_with_tensorboard.md
docs/user/pixel_observations.md
docs/user/preparing_a_pr.md
docs/user/references.bib
docs/user/reuse_garage_policy.md
docs/user/sampling.md
docs/user/save_load_resume_exp.md
docs/user/setting_up_your_development_environment.md
docs/user/testing.md
docs/user/training_a_policy.md
docs/user/use_pretrained_network_to_start_new_experiment.md
docs/user/writing_documentation.md
docs/user/images/bc_meanLoss.png
docs/user/images/bc_stdLoss.png
docs/user/images/dqn_plots.png
docs/user/images/numpy.png
docs/user/images/pytorch.png
src/garage.egg-info/PKG-INFO
src/garage.egg-info/SOURCES.txt
src/garage.egg-info/dependency_links.txt
src/garage.egg-info/requires.txt
src/garage.egg-info/top_level.txt
