Metadata-Version: 2.1
Name: garage
Version: 2021.3.0
Summary: A toolkit for reproducible reinforcement learning research
Home-page: https://github.com/rlworkgroup/garage
Author: Reinforcement Learning Working Group
License: MIT
Platform: UNKNOWN
Classifier: Development Status :: 4 - Beta
Classifier: Intended Audience :: Developers
Classifier: Intended Audience :: Education
Classifier: Intended Audience :: Science/Research
Classifier: License :: OSI Approved :: MIT License
Classifier: Programming Language :: Python :: 3.6
Classifier: Programming Language :: Python :: 3.7
Classifier: Programming Language :: Python :: 3.8
Classifier: Programming Language :: Python :: 3 :: Only
Classifier: Topic :: Scientific/Engineering :: Artificial Intelligence
Classifier: Topic :: Scientific/Engineering :: Mathematics
Classifier: Topic :: Software Development :: Libraries
Requires-Python: >=3.6
Provides-Extra: gym
Provides-Extra: mujoco
Provides-Extra: dm_control
Provides-Extra: bullet
Provides-Extra: all
Provides-Extra: dev
